bakers_registry/__init__.py
bakers_registry/cli.py
bakers_registry/colored.py
bakers_registry/core.py
bakers_registry/encoding.py
bakers_registry-0.2.1.dist-info/entry_points.txt
bakers_registry-0.2.1.dist-info/LICENSE
bakers_registry-0.2.1.dist-info/WHEEL
bakers_registry-0.2.1.dist-info/METADATA
bakers_registry-0.2.1.dist-info/RECORD
