Metadata-Version: 2.1
Name: bakers-registry
Version: 0.2.1
Summary: Command line interface for the Tezos Bakers Registry
Home-page: https://github.com/baking-bad/bakers-registry-cli
License: MIT
Keywords: tezos,crypto,blockchain,xtz
Author: Michael Zaikin
Author-email: mz@baking-bad.org
Requires-Python: >=3.7,<4.0
Classifier: License :: OSI Approved :: MIT License
Classifier: Operating System :: OS Independent
Classifier: Programming Language :: Python :: 3
Classifier: Programming Language :: Python :: 3.7
Classifier: Programming Language :: Python :: 3.8
Classifier: Programming Language :: Python :: 3.9
Requires-Dist: conseil
Requires-Dist: jsondiff
Requires-Dist: pytezos
Requires-Dist: yaspin
Project-URL: Repository, https://github.com/baking-bad/bakers-registry-cli
